napari_mm3/__init__.py
napari_mm3/_annotate.py
napari_mm3/_channel_picker.py
napari_mm3/_colors.py
napari_mm3/_compile.py
napari_mm3/_deriving_widgets.py
napari_mm3/_foci.py
napari_mm3/_foci_picking.py
napari_mm3/_segment_otsu.py
napari_mm3/_segment_unet.py
napari_mm3/_subtract.py
napari_mm3/_tiff_converter.py
napari_mm3/_track.py
napari_mm3/_train_unet.py
napari_mm3/napari.yaml
napari_mm3/utils.py
napari_mm3/utils_plotting.py
napari_mm3/_tests/__init__.py
napari_mm3/_tests/test_placeholder.py
napari_mm3-0.0.16.dist-info/LICENSE
napari_mm3-0.0.16.dist-info/METADATA
napari_mm3-0.0.16.dist-info/WHEEL
napari_mm3-0.0.16.dist-info/entry_points.txt
napari_mm3-0.0.16.dist-info/top_level.txt
napari_mm3-0.0.16.dist-info/RECORD
