Metadata-Version: 2.1
Name: napari-mm3
Version: 0.0.16
Summary: a plugin for mother machine image analysis
Home-page: https://github.com/junlabucsd/napari-mm3
Author: Gursharan Ahir, Michael Sandler, Ryan Thiermann
Author-email: ryan.thiermann@gmail.com
License: BSD-3-Clause
Project-URL: Bug Tracker, https://github.com/junlabucsd/napari-mm3/issues
Project-URL: Documentation, https://github.com/junlabucsd/napari-mm3#README.md
Project-URL: Source Code, https://github.com/junlabucsd/napari-mm3
Project-URL: User Support, https://github.com/junlabucsd/napari-mm3/issues
Classifier: Development Status :: 2 - Pre-Alpha
Classifier: Intended Audience :: Developers
Classifier: Framework :: napari
Classifier: Topic :: Software Development :: Testing
Classifier: Programming Language :: Python
Classifier: Programming Language :: Python :: 3
Classifier: Programming Language :: Python :: 3.9
Classifier: Programming Language :: Python :: 3.10
Classifier: Programming Language :: Python :: 3.11
Classifier: Operating System :: OS Independent
Classifier: License :: OSI Approved :: BSD License
Requires-Python: >=3.9
License-File: LICENSE
Requires-Dist: napari-plugin-engine >=0.1.4
Requires-Dist: numpy
Requires-Dist: h5py
Requires-Dist: tifffile ==2021.11.2
Requires-Dist: scikit-learn
Requires-Dist: scikit-image
Requires-Dist: tensorflow
Requires-Dist: nd2reader
Requires-Dist: seaborn
Requires-Dist: elasticdeform
